{
  "Basic_Information": {
    "name": "PEPE Token",
    "website": "",
    "description": "big meme",
    "explorer": "https://testnet.xscscan.com/",
    "type": "ERC20",
    "symbol": "PEPE",
    "decimals": 18,
    "status": "active",
    "id": "0xbe84b1c3f9A39Ce44F64b1aB434BFBFB5Aa791d5"
  },
  "Social_Profiles": {
    "twitter": "",
    "telegram": "",
    "reddit": "",
    "discord": "",
    "slack": "",
    "instagram": "",
    "wechat": "",
    "facebook": "",
    "medium": "",
    "github": "",
    "blog": "",
    "bitcointalk": "",
    "youtube": "",
    "tiktok": "",
    "forum": "",
    "linkedin": "",
    "opensea": ""
  },
  "Price_Data": {
    "coinMarketCap": "",
    "coinGecko": "",
    "ave": ""
  }
}
